imagerouter/__init__.py
imagerouter/cli.py
imagerouter/client.py
imagerouter/estimator.py
imagerouter/exceptions.py
imagerouter/models.py
imagerouter/utils.py
imagerouter/generators/__init__.py
imagerouter/generators/image.py
imagerouter/generators/video.py
imagerouter-0.7.3.dist-info/METADATA
imagerouter-0.7.3.dist-info/WHEEL
imagerouter-0.7.3.dist-info/entry_points.txt
imagerouter-0.7.3.dist-info/top_level.txt
imagerouter-0.7.3.dist-info/RECORD
