Metadata-Version: 2.4
Name: imagerouter
Version: 0.7.3
Summary: Python module for video and image generation via ImageRouter.io unified API
Author-email: ImageRouter <support@imagerouter.io>
License-Expression: MIT
Project-URL: Homepage, https://imagerouter.io
Project-URL: Documentation, https://docs.imagerouter.io
Project-URL: Blog, https://kamaskera.com
Classifier: Development Status :: 4 - Beta
Classifier: Intended Audience :: Developers
Classifier: Programming Language :: Python :: 3
Classifier: Programming Language :: Python :: 3.10
Classifier: Programming Language :: Python :: 3.11
Classifier: Programming Language :: Python :: 3.12
Requires-Python: >=3.10
Requires-Dist: requests>=2.28.0
Requires-Dist: python-dotenv>=1.0.0
Provides-Extra: dev
Requires-Dist: pytest>=7.0.0; extra == "dev"
Requires-Dist: pytest-cov>=4.0.0; extra == "dev"
Requires-Dist: mypy>=1.0.0; extra == "dev"
Requires-Dist: ruff>=0.1.0; extra == "dev"
Requires-Dist: types-requests>=2.28.0; extra == "dev"
